dockvirt/__init__.py
dockvirt/cli.py
dockvirt/config.py
dockvirt/doctor.py
dockvirt/image_generator.py
dockvirt/image_manager.py
dockvirt/logdb.py
dockvirt/self_heal.py
dockvirt/system_check.py
dockvirt/vm_manager.py
dockvirt/templates/Caddyfile-https.json.j2
dockvirt/templates/Caddyfile.j2
dockvirt/templates/cloud-init.yaml.j2
dockvirt/templates/docker-compose-https.yml.j2
dockvirt/templates/docker-compose.yml.j2
dockvirt-0.1.12.dist-info/licenses/LICENSE
dockvirt-0.1.12.dist-info/METADATA
dockvirt-0.1.12.dist-info/WHEEL
dockvirt-0.1.12.dist-info/entry_points.txt
dockvirt-0.1.12.dist-info/top_level.txt
dockvirt-0.1.12.dist-info/RECORD
